tricircleclient/__init__.py
tricircleclient/client.py
tricircleclient/constants.py
tricircleclient/exceptions.py
tricircleclient/osc.py
tricircleclient/utils.py
tricircleclient/version.py
tricircleclient/tests/__init__.py
tricircleclient/tests/unit/__init__.py
tricircleclient/tests/unit/fakes.py
tricircleclient/tests/unit/test_exceptions.py
tricircleclient/tests/unit/utils.py
tricircleclient/tests/unit/v1/__init__.py
tricircleclient/tests/unit/v1/test_jobs_cli.py
tricircleclient/tests/unit/v1/test_pods_cli.py
tricircleclient/tests/unit/v1/test_routings_cli.py
tricircleclient/v1/__init__.py
tricircleclient/v1/base.py
tricircleclient/v1/client.py
tricircleclient/v1/jobs.py
tricircleclient/v1/jobs_cli.py
tricircleclient/v1/pods.py
tricircleclient/v1/pods_cli.py
tricircleclient/v1/routings.py
tricircleclient/v1/routings_cli.py
tricircleclient-1.0.0.dist-info/AUTHORS
tricircleclient-1.0.0.dist-info/LICENSE
tricircleclient-1.0.0.dist-info/METADATA
tricircleclient-1.0.0.dist-info/WHEEL
tricircleclient-1.0.0.dist-info/entry_points.txt
tricircleclient-1.0.0.dist-info/pbr.json
tricircleclient-1.0.0.dist-info/top_level.txt
tricircleclient-1.0.0.dist-info/RECORD
